{
  "$schema": "https://mintlify.com/schema.json",
  "theme": "mint",
  "name": "Rubric AI Talent Portal",
  "logo": {
    "dark": "/logo/dark.svg",
    "light": "/logo/light.svg"
  },
  "favicon": "/favicon.svg",
  "colors": {
    "primary": "#6d5ef6",
    "light": "#8b7ff7",
    "dark": "#5a4dd4",
    "anchors": {
      "from": "#6d5ef6",
      "to": "#8b7ff7"
    }
  },
  "topbarLinks": [
    {
      "name": "Support",
      "url": "mailto:support@rubric.ai"
    }
  ],
  "topbarCtaButton": {
    "name": "Portal",
    "url": "https://talent.rubric.ai"
  },
  "tabs": [
    {
      "name": "How To",
      "url": "how-to"
    },
    {
      "name": "Working with Rubric AI",
      "url": "working"
    },
    {
      "name": "Policies",
      "url": "policies"
    },
    {
      "name": "Support",
      "url": "support"
    }
  ],
  "anchors": [
    {
      "name": "Talent Portal",
      "icon": "house",
      "url": "https://talent.rubric.ai"
    },
    {
      "name": "Contact Support",
      "icon": "envelope",
      "url": "mailto:support@rubric.ai"
    }
  ],
  "navigation": [
    {
      "group": "Welcome",
      "pages": ["introduction"]
    },
    {
      "group": "How To",
      "pages": [
        "how-to/create-account",
        "how-to/setup-profile",
        "how-to/apply",
        "how-to/payments",
        "how-to/referrals"
      ]
    },
    {
      "group": "Working with Rubric AI",
      "pages": [
        "working/getting-started",
        "working/onboarding",
        "working/offboarding"
      ]
    },
    {
      "group": "Policies",
      "pages": ["policies/overview"]
    },
    {
      "group": "Support",
      "pages": ["support/faq"]
    }
  ],
  "footerSocials": {
    "website": "https://rubric.ai"
  }
}
